voicepeak_wrapper/__init__.py
voicepeak_wrapper/voicepeak.py
voicepeak_wrapper-1.1.1.dist-info/licenses/LICENSE
voicepeak_wrapper-1.1.1.dist-info/METADATA
voicepeak_wrapper-1.1.1.dist-info/WHEEL
voicepeak_wrapper-1.1.1.dist-info/top_level.txt
voicepeak_wrapper-1.1.1.dist-info/RECORD
