Metadata-Version: 2.4
Name: voicepeak_wrapper
Version: 1.1.1
Summary: VOICEPEAKの非公式ラッパーです。詳しくはHomepage(Github)をご覧ください
Author: Nanahuse
License: MIT License
Project-URL: Homepage, https://github.com/Nanahuse/VoicepeakWrapper
Classifier: License :: OSI Approved :: MIT License
Classifier: Programming Language :: Python :: 3.10
Classifier: Programming Language :: Python :: 3.11
Requires-Python: >=3.10
License-File: LICENSE
Provides-Extra: dev
Requires-Dist: pytest; extra == "dev"
Requires-Dist: pytest-asyncio; extra == "dev"
Requires-Dist: flake8; extra == "dev"
Requires-Dist: black; extra == "dev"
Requires-Dist: isort; extra == "dev"
Requires-Dist: mypy; extra == "dev"
Dynamic: license-file
